dexscraper/__init__.py
dexscraper/_version.py
dexscraper/cli.py
dexscraper/cloudflare_bypass.py
dexscraper/config.py
dexscraper/enhanced_protocol.py
dexscraper/logger.py
dexscraper/models.py
dexscraper/protocol.py
dexscraper/scraper.py
dexscraper/utils.py
dexscraper-0.1.1.dev0.dist-info/licenses/LICENSE
dexscraper-0.1.1.dev0.dist-info/METADATA
dexscraper-0.1.1.dev0.dist-info/WHEEL
dexscraper-0.1.1.dev0.dist-info/entry_points.txt
dexscraper-0.1.1.dev0.dist-info/top_level.txt
dexscraper-0.1.1.dev0.dist-info/RECORD
